edu_matematica/__init__.py
edu_matematica/educacao_fisica.py
edu_matematica/matematica.py
edu_matematica-0.1.0.dist-info/licenses/LICENSE
edu_matematica-0.1.0.dist-info/METADATA
edu_matematica-0.1.0.dist-info/WHEEL
edu_matematica-0.1.0.dist-info/top_level.txt
edu_matematica-0.1.0.dist-info/RECORD
