Metadata-Version: 2.4
Name: edu-matematica
Version: 0.1.0
Summary: Biblioteca de Matemática e Educação Física — cálculos, IMC e médias.
Author-email: Luiz Gustavo Santana Casemiro <seuemail@exemplo.com>
License: MIT
Project-URL: Homepage, https://github.com/seuusuario/edu_matematica
Keywords: matematica,educacao fisica,imc,media
Classifier: Programming Language :: Python :: 3
Classifier: License :: OSI Approved :: MIT License
Classifier: Operating System :: OS Independent
Requires-Python: >=3.7
License-File: LICENSE
Dynamic: license-file
